{"dependencies":[{"name":"./../src/index.js","dynamic":true}],"generated":{"html":"<!DOCTYPE html>\n<html lang=\"en\">\n\n<head>\n    <meta charset=\"UTF-8\">\n    <meta name=\"viewport\" content=\"width=device-width, initial-scale=1.0\">\n    <meta http-equiv=\"X-UA-Compatible\" content=\"ie=edge\">\n    <title>ES6</title>\n</head>\n\n<body>\n    <div id=\"app\"></div>\n    <script src=\"/dist/e36d7d21e9cb6f851326d421f2f7a9b7.js\"></script>\n</body>\n\n</html>"},"hash":"59c13f04ef45d2974b3c4f06a39fa29b","cacheData":{}}